README.md
setup.py
cmu_multimodal_sdk.egg-info/PKG-INFO
cmu_multimodal_sdk.egg-info/SOURCES.txt
cmu_multimodal_sdk.egg-info/dependency_links.txt
cmu_multimodal_sdk.egg-info/requires.txt
cmu_multimodal_sdk.egg-info/top_level.txt
mmsdk/__init__.py
mmsdk/mmdatasdk/__init__.py
mmsdk/mmdatasdk/computational_sequence/__init__.py
mmsdk/mmdatasdk/computational_sequence/blank.py
mmsdk/mmdatasdk/computational_sequence/computational_sequence.py
mmsdk/mmdatasdk/computational_sequence/download_ops.py
mmsdk/mmdatasdk/computational_sequence/file_ops.py
mmsdk/mmdatasdk/computational_sequence/integrity_check.py
mmsdk/mmdatasdk/configurations/__init__.py
mmsdk/mmdatasdk/configurations/metadataconfigs.py
mmsdk/mmdatasdk/dataset/__init__.py
mmsdk/mmdatasdk/dataset/dataset.py
mmsdk/mmdatasdk/dataset/standard_datasets/__init__.py
mmsdk/mmdatasdk/dataset/standard_datasets/CMU_MOSEI/__init__.py
mmsdk/mmdatasdk/dataset/standard_datasets/CMU_MOSEI/cmu_mosei.py
mmsdk/mmdatasdk/dataset/standard_datasets/CMU_MOSEI/cmu_mosei_std_folds.py
mmsdk/mmdatasdk/dataset/standard_datasets/CMU_MOSI/__init__.py
mmsdk/mmdatasdk/dataset/standard_datasets/CMU_MOSI/cmu_mosi.py
mmsdk/mmdatasdk/dataset/standard_datasets/CMU_MOSI/cmu_mosi_std_folds.py
mmsdk/mmdatasdk/dataset/standard_datasets/POM/__init__.py
mmsdk/mmdatasdk/dataset/standard_datasets/POM/pom.py
mmsdk/mmdatasdk/dataset/standard_datasets/POM/pom_std_folds.py
mmsdk/mmdatasdk/dataset/standard_datasets/SocialIQ/__init__.py
mmsdk/mmdatasdk/dataset/standard_datasets/SocialIQ/socialiq.py
mmsdk/mmdatasdk/dataset/standard_datasets/SocialIQ/socialiq_std_folds.py
mmsdk/mmdatasdk/log/__init__.py
mmsdk/mmdatasdk/log/log.py
mmsdk/mmmodelsdk/__init__.py
mmsdk/mmmodelsdk/fusion/__init__.py
mmsdk/mmmodelsdk/fusion/dynamic_fusion_graph/__init__.py
mmsdk/mmmodelsdk/fusion/dynamic_fusion_graph/model.py
mmsdk/mmmodelsdk/fusion/multiple_attention/__init__.py
mmsdk/mmmodelsdk/fusion/multiple_attention/model.py
mmsdk/mmmodelsdk/fusion/recurrent_fusion/__init__.py
mmsdk/mmmodelsdk/fusion/recurrent_fusion/model.py
mmsdk/mmmodelsdk/fusion/tensor_fusion/__init__.py
mmsdk/mmmodelsdk/fusion/tensor_fusion/model.py
mmsdk/mmmodelsdk/modules/__init__.py
