Metadata-Version: 1.0
Name: cmu-multimodal-sdk
Version: 0.0.2
Summary: a copy of cmu-multimodal-sdk
Home-page: https://github.com/lizhaoliu-Lec/CMU-MultimodalSDK
Author: Lec
Author-email: 2524463910@qq.com
License: UNKNOWN
Platform: UNKNOWN
